impossible/__init__.py
impossible-0.1.0.dist-info/METADATA
impossible-0.1.0.dist-info/WHEEL
impossible-0.1.0.dist-info/top_level.txt
impossible-0.1.0.dist-info/RECORD
