Metadata-Version: 2.1
Name: impossible
Version: 0.1.0
Summary: Impossible is an Encoder/Decoder.
Home-page: https://github.com/mathstar13/impossible
Author: Mathstar13
Project-URL: Bug Tracker, https://github.com/mathstar13/impossible/issues
Classifier: Programming Language :: Python :: 3
Classifier: License :: OSI Approved :: MIT License
Classifier: Operating System :: OS Independent
Requires-Python: >=3.6
